textpredict/__init__.py
textpredict/benchmarking.py
textpredict/cli.py
textpredict/config.py
textpredict/datasets.py
textpredict/evaluation.py
textpredict/evaluators/__init__.py
textpredict/evaluators/base_evaluator.py
textpredict/evaluators/seq2seq_evaluator.py
textpredict/evaluators/sequence_classification_evaluator.py
textpredict/evaluators/token_classification_evaluator.py
textpredict/explainability.py
textpredict/logger.py
textpredict/model_comparison.py
textpredict/model_loader.py
textpredict/predictor.py
textpredict/task_models/__init__.py
textpredict/task_models/base.py
textpredict/task_models/emotion.py
textpredict/task_models/ner.py
textpredict/task_models/sentiment.py
textpredict/task_models/seq2seq.py
textpredict/task_models/sequence_classification.py
textpredict/task_models/token_classification.py
textpredict/task_models/zeroshot.py
textpredict/trainers/__init__.py
textpredict/trainers/base_trainer.py
textpredict/trainers/seq2seq_trainer.py
textpredict/trainers/sequence_classification_trainer.py
textpredict/trainers/token_classification_trainer.py
textpredict/utils/__init__.py
textpredict/utils/callbacks.py
textpredict/utils/data_preprocessing.py
textpredict/utils/error_handling.py
textpredict/utils/hyperparameter_tuning.py
textpredict/visualization.py
textpredict-0.1.3.dist-info/LICENSE
textpredict-0.1.3.dist-info/METADATA
textpredict-0.1.3.dist-info/WHEEL
textpredict-0.1.3.dist-info/RECORD
