Metadata-Version: 2.1
Name: textpredict
Version: 0.1.3
Summary: TextPredict is a powerful Python package designed for various text analysis and prediction tasks using advanced NLP models. It simplifies the process of performing sentiment analysis, emotion detection, zero-shot classification, named entity recognition (NER), and more.
Home-page: https://github.com/ankit-aglawe/textpredict
License: MIT
Keywords: text classification,emotion classification,sentiment analysis,text analysis,machine learning,NLP,transformers,data science,pre-trained models,text mining
Author: Ankit Aglawe
Author-email: aglawe.ankit@gmail.com
Requires-Python: >=3.9,<4.0
Classifier: License :: OSI Approved :: MIT License
Classifier: Programming Language :: Python :: 3
Classifier: Programming Language :: Python :: 3.9
Classifier: Programming Language :: Python :: 3.10
Classifier: Programming Language :: Python :: 3.11
Classifier: Programming Language :: Python :: 3.12
Requires-Dist: click (>=8.0.1,<9.0.0)
Requires-Dist: datasets (>=1.11.0,<2.0.0)
Requires-Dist: fastapi (>=0.68,<0.110)
Requires-Dist: matplotlib (>=3.4.3,<4.0.0)
Requires-Dist: optuna (>=2.9.1,<3.0.0)
Requires-Dist: plotly (>=5.22.0,<6.0.0)
Requires-Dist: scikit-learn (>=1.5.1,<2.0.0)
Requires-Dist: torch (>=1.9.0,<2.0.0)
Requires-Dist: transformers (>=4.9.0,<5.0.0)
Requires-Dist: uvicorn (>=0.15.0,<0.16.0)
Project-URL: Changelog, https://github.com/ankit-aglawe/textpredict/releases
Project-URL: Documentation, https://github.com/ankit-aglawe/textpredict#readme
Project-URL: Repository, https://github.com/ankit-aglawe/textpredict
Project-URL: Source, https://github.com/ankit-aglawe/textpredict
Project-URL: Tracker, https://github.com/ankit-aglawe/textpredict/issues
